cakegeminiapi/__init__.py
cakegeminiapi/__main__.py
cakegeminiapi/cake.py
cakegeminiapi/core.py
cakegeminiapi/core_old.py
cakegeminiapi/main.py
cakegeminiapi/prompts.py
cakegeminiapi-0.1.8.dist-info/METADATA
cakegeminiapi-0.1.8.dist-info/WHEEL
cakegeminiapi-0.1.8.dist-info/entry_points.txt
cakegeminiapi-0.1.8.dist-info/top_level.txt
cakegeminiapi-0.1.8.dist-info/RECORD
