Metadata-Version: 2.4
Name: cakegeminiapi
Version: 0.1.8
Requires-Python: >=3.7
Requires-Dist: setuptools>=65.5.1
Requires-Dist: wheel>=0.38.4
Requires-Dist: build>=0.10.0
Requires-Dist: twine>=4.0.2
Requires-Dist: pydantic>=2.0.0
Requires-Dist: requests>=2.31.0
Requires-Dist: typing-extensions>=4.5.0
Requires-Dist: google-generativeai
Requires-Dist: tqdm>=4.65.0
Requires-Dist: google-genai>=1.24.0
Requires-Dist: httpx[socks]
Dynamic: requires-dist
Dynamic: requires-python
